Metadata-Version: 2.1
Name: molecular
Version: 0.2.5
Summary: A toolkit for molecular dynamics simulations
Home-page: https://www.lockhartlab.org
Author: C. Lockhart
Author-email: chris@lockhartlab.org
License-File: LICENSE.md
Requires-Dist: Cython
Requires-Dist: glovebox
Requires-Dist: hypothesis (>=5.6.0)
Requires-Dist: iox (>=0.3.dev13)
Requires-Dist: llvmlite
Requires-Dist: numba (>=0.48.0)
Requires-Dist: numpy
Requires-Dist: pandas
Requires-Dist: pyarrow
Requires-Dist: pyyaml (>=5.3)
Requires-Dist: scipy
Requires-Dist: statsmodels
Requires-Dist: sympy
Requires-Dist: tqdm
Requires-Dist: matplotlib (>=3.1.3)
Requires-Dist: setuptools
Requires-Dist: sparse
Requires-Dist: uplot
